[
    {
        "1": 0,
        "2": 0,
        "3": 11,
        "4": 109,
        "5": 692,
        "6": 2504,
        "7": 1728,
        "8": 1426,
        "matches": 10000
    },
    {
        "1": 0,
        "2": 0,
        "3": 3,
        "4": 41,
        "5": 269,
        "6": 958,
        "7": 803,
        "8": 653
    },
    {
        "1": 0,
        "2": 0,
        "3": 7,
        "4": 59,
        "5": 375,
        "6": 1322,
        "7": 763,
        "8": 647
    },
    {
        "1": 0,
        "2": 0,
        "3": 1,
        "4": 9,
        "5": 48,
        "6": 224,
        "7": 162,
        "8": 126
    },
    {
        "hammer_start": {
            "wins": 2411,
            "draws": 417,
            "losses": 2182,
            "matches": 5010
        },
        "no_hammer_start": {
            "wins": 2394,
            "draws": 399,
            "losses": 2197,
            "matches": 4990
        }
    }
]